cloner/__init__.py
cloner/arg_parser.py
cloner/cli.py
cloner-1.0.3.dist-info/LICENSE
cloner-1.0.3.dist-info/METADATA
cloner-1.0.3.dist-info/WHEEL
cloner-1.0.3.dist-info/entry_points.txt
cloner-1.0.3.dist-info/top_level.txt
cloner-1.0.3.dist-info/RECORD
