Metadata-Version: 2.1
Name: cloner
Version: 1.0.3
Summary: A tiny utility for cloning github repos
Home-page: https://github.com/kardasis/cloner
Author: Ari Kardasis
Author-email: ari.kardasis@gmail.com
License: UNKNOWN
Platform: UNKNOWN
Classifier: Programming Language :: Python :: 3
Classifier: License :: OSI Approved :: MIT License
Classifier: Operating System :: OS Independent
Requires-Python: >=3.7
Requires-Dist: Click
